docstring_expander/__init__.py
docstring_expander/constants.py
docstring_expander/expander.py
docstring_expander/kwarg.py
docstring_expander-0.1.dist-info/LICENSE
docstring_expander-0.1.dist-info/METADATA
docstring_expander-0.1.dist-info/WHEEL
docstring_expander-0.1.dist-info/top_level.txt
docstring_expander-0.1.dist-info/RECORD
