Metadata-Version: 2.1
Name: docstring-expander
Version: 0.1
Summary: Enables intellisense for **kwargs
Home-page: https://github.com/joseph-hellerstein/docstring_expander.git
Author: Joseph L. Hellerstein
Author-email: jlheller@uw.edu
License: UNKNOWN
Platform: UNKNOWN
